<?xml version="1.0" encoding="utf-8"?>
<TextureAtlas imagePath="TulipSit.png">
	<!-- Created with Adobe Animate version 22.0.5.191 -->
	<!-- http://www.adobe.com/products/animate.html -->
	<SubTexture name="TulipDown0000" x="10" y="10" width="176" height="209"/>
	<SubTexture name="TulipDown0001" x="10" y="10" width="176" height="209"/>
	<SubTexture name="TulipDown0002" x="196" y="10" width="176" height="209"/>
	<SubTexture name="TulipDown0003" x="196" y="10" width="176" height="209"/>
	<SubTexture name="TulipDown0004" x="382" y="10" width="176" height="209"/>
	<SubTexture name="TulipDown0005" x="382" y="10" width="176" height="209"/>
	<SubTexture name="TulipDown0006" x="568" y="10" width="176" height="209"/>
	<SubTexture name="TulipDown0007" x="568" y="10" width="176" height="209"/>
	<SubTexture name="TulipDown0008" x="568" y="10" width="176" height="209"/>
	<SubTexture name="TulipDown0009" x="568" y="10" width="176" height="209"/>
	<SubTexture name="TulipDown0010" x="568" y="10" width="176" height="209"/>
	<SubTexture name="TulipDown0011" x="568" y="10" width="176" height="209"/>
	<SubTexture name="TulipDown0012" x="568" y="10" width="176" height="209"/>
	<SubTexture name="TulipDown0013" x="568" y="10" width="176" height="209"/>
	<SubTexture name="TulipDown0014" x="568" y="10" width="176" height="209"/>
	<SubTexture name="TulipDown0015" x="568" y="10" width="176" height="209"/>
	<SubTexture name="TulipDown0016" x="568" y="10" width="176" height="209"/>
	<SubTexture name="TulipDown0017" x="568" y="10" width="176" height="209"/>
	<SubTexture name="TulipDown0018" x="568" y="10" width="176" height="209"/>
	<SubTexture name="TulipDown0019" x="568" y="10" width="176" height="209"/>
	<SubTexture name="TulipLeft0000" x="754" y="10" width="182" height="207"/>
	<SubTexture name="TulipLeft0001" x="754" y="10" width="182" height="207"/>
	<SubTexture name="TulipLeft0002" x="946" y="10" width="182" height="207"/>
	<SubTexture name="TulipLeft0003" x="946" y="10" width="182" height="207"/>
	<SubTexture name="TulipLeft0004" x="1138" y="10" width="182" height="207"/>
	<SubTexture name="TulipLeft0005" x="1138" y="10" width="182" height="207"/>
	<SubTexture name="TulipLeft0006" x="1330" y="10" width="182" height="207"/>
	<SubTexture name="TulipLeft0007" x="1330" y="10" width="182" height="207"/>
	<SubTexture name="TulipLeft0008" x="1330" y="10" width="182" height="207"/>
	<SubTexture name="TulipLeft0009" x="1330" y="10" width="182" height="207"/>
	<SubTexture name="TulipLeft0010" x="1330" y="10" width="182" height="207"/>
	<SubTexture name="TulipLeft0011" x="1330" y="10" width="182" height="207"/>
	<SubTexture name="TulipLeft0012" x="1330" y="10" width="182" height="207"/>
	<SubTexture name="TulipLeft0013" x="1330" y="10" width="182" height="207"/>
	<SubTexture name="TulipLeft0014" x="1330" y="10" width="182" height="207"/>
	<SubTexture name="TulipLeft0015" x="1330" y="10" width="182" height="207"/>
	<SubTexture name="TulipLeft0016" x="1330" y="10" width="182" height="207"/>
	<SubTexture name="TulipLeft0017" x="1330" y="10" width="182" height="207"/>
	<SubTexture name="TulipLeft0018" x="1330" y="10" width="182" height="207"/>
	<SubTexture name="TulipLeft0019" x="1330" y="10" width="182" height="207"/>
	<SubTexture name="TulipRight0000" x="1522" y="10" width="166" height="204"/>
	<SubTexture name="TulipRight0001" x="1522" y="10" width="166" height="204"/>
	<SubTexture name="TulipRight0002" x="1698" y="10" width="166" height="204"/>
	<SubTexture name="TulipRight0003" x="1698" y="10" width="166" height="204"/>
	<SubTexture name="TulipRight0004" x="10" y="229" width="166" height="204"/>
	<SubTexture name="TulipRight0005" x="10" y="229" width="166" height="204"/>
	<SubTexture name="TulipRight0006" x="186" y="229" width="166" height="204"/>
	<SubTexture name="TulipRight0007" x="186" y="229" width="166" height="204"/>
	<SubTexture name="TulipRight0008" x="186" y="229" width="166" height="204"/>
	<SubTexture name="TulipRight0009" x="186" y="229" width="166" height="204"/>
	<SubTexture name="TulipRight0010" x="186" y="229" width="166" height="204"/>
	<SubTexture name="TulipRight0011" x="186" y="229" width="166" height="204"/>
	<SubTexture name="TulipRight0012" x="186" y="229" width="166" height="204"/>
	<SubTexture name="TulipRight0013" x="186" y="229" width="166" height="204"/>
	<SubTexture name="TulipRight0014" x="186" y="229" width="166" height="204"/>
	<SubTexture name="TulipRight0015" x="186" y="229" width="166" height="204"/>
	<SubTexture name="TulipRight0016" x="186" y="229" width="166" height="204"/>
	<SubTexture name="TulipRight0017" x="186" y="229" width="166" height="204"/>
	<SubTexture name="TulipRight0018" x="186" y="229" width="166" height="204"/>
	<SubTexture name="TulipRight0019" x="186" y="229" width="166" height="204"/>
	<SubTexture name="TulipUp0000" x="362" y="229" width="178" height="210"/>
	<SubTexture name="TulipUp0001" x="362" y="229" width="178" height="210"/>
	<SubTexture name="TulipUp0002" x="550" y="229" width="178" height="210"/>
	<SubTexture name="TulipUp0003" x="550" y="229" width="178" height="210"/>
	<SubTexture name="TulipUp0004" x="738" y="229" width="178" height="210"/>
	<SubTexture name="TulipUp0005" x="738" y="229" width="178" height="210"/>
	<SubTexture name="TulipUp0006" x="926" y="229" width="178" height="210"/>
	<SubTexture name="TulipUp0007" x="926" y="229" width="178" height="210"/>
	<SubTexture name="TulipUp0008" x="1114" y="229" width="178" height="210"/>
	<SubTexture name="TulipUp0009" x="1114" y="229" width="178" height="210"/>
	<SubTexture name="TulipUp0010" x="1114" y="229" width="178" height="210"/>
	<SubTexture name="TulipUp0011" x="1114" y="229" width="178" height="210"/>
	<SubTexture name="TulipUp0012" x="1114" y="229" width="178" height="210"/>
	<SubTexture name="TulipUp0013" x="1114" y="229" width="178" height="210"/>
	<SubTexture name="TulipUp0014" x="1114" y="229" width="178" height="210"/>
	<SubTexture name="TulipUp0015" x="1114" y="229" width="178" height="210"/>
	<SubTexture name="TulipUp0016" x="1114" y="229" width="178" height="210"/>
	<SubTexture name="TulipUp0017" x="1114" y="229" width="178" height="210"/>
	<SubTexture name="TulipUp0018" x="1114" y="229" width="178" height="210"/>
	<SubTexture name="TulipUp0019" x="1114" y="229" width="178" height="210"/>
	<SubTexture name="Tulip_Idle0000" x="1302" y="229" width="178" height="205"/>
	<SubTexture name="Tulip_Idle0001" x="1302" y="229" width="178" height="205"/>
	<SubTexture name="Tulip_Idle0002" x="1302" y="229" width="178" height="205"/>
	<SubTexture name="Tulip_Idle0003" x="1302" y="229" width="178" height="205"/>
	<SubTexture name="Tulip_Idle0004" x="1302" y="229" width="178" height="205"/>
	<SubTexture name="Tulip_Idle0005" x="1302" y="229" width="178" height="205"/>
	<SubTexture name="Tulip_Idle0006" x="1302" y="229" width="178" height="205"/>
	<SubTexture name="Tulip_Idle0007" x="1302" y="229" width="178" height="205"/>
	<SubTexture name="Tulip_Idle0008" x="1302" y="229" width="178" height="205"/>
	<SubTexture name="Tulip_Idle0009" x="1302" y="229" width="178" height="205"/>
	<SubTexture name="Tulip_Idle0010" x="1302" y="229" width="178" height="205"/>
	<SubTexture name="Tulip_Idle0011" x="1302" y="229" width="178" height="205"/>
	<SubTexture name="Tulip_Idle0012" x="1302" y="229" width="178" height="205"/>
	<SubTexture name="Tulip_Idle0013" x="1302" y="229" width="178" height="205"/>
	<SubTexture name="Tulip_Idle0014" x="1302" y="229" width="178" height="205"/>
	<SubTexture name="Tulip_Idle0015" x="1302" y="229" width="178" height="205"/>
	<SubTexture name="Tulip_Idle0016" x="1490" y="229" width="178" height="205"/>
	<SubTexture name="Tulip_Idle0017" x="1490" y="229" width="178" height="205"/>
	<SubTexture name="Tulip_Idle0018" x="1678" y="229" width="178" height="205"/>
	<SubTexture name="Tulip_Idle0019" x="1678" y="229" width="178" height="205"/>
	<SubTexture name="Tulip_Idle0020" x="10" y="449" width="178" height="205"/>
	<SubTexture name="Tulip_Idle0021" x="10" y="449" width="178" height="205"/>
	<SubTexture name="Tulip_Idle0022" x="198" y="449" width="178" height="205"/>
	<SubTexture name="Tulip_Idle0023" x="198" y="449" width="178" height="205"/>
	<SubTexture name="Tulip_Idle0024" x="386" y="449" width="178" height="205"/>
	<SubTexture name="Tulip_Idle0025" x="386" y="449" width="178" height="205"/>
	<SubTexture name="Tulip_Idle0026" x="574" y="449" width="178" height="205"/>
	<SubTexture name="Tulip_Idle0027" x="574" y="449" width="178" height="205"/>
	<SubTexture name="Tulip_Idle0028" x="762" y="449" width="178" height="205"/>
	<SubTexture name="Tulip_Idle0029" x="762" y="449" width="178" height="205"/>
	<SubTexture name="Tulip_Idle0030" x="762" y="449" width="178" height="205"/>
	<SubTexture name="Tulip_Idle0031" x="762" y="449" width="178" height="205"/>
	<SubTexture name="Tulip_Idle0032" x="762" y="449" width="178" height="205"/>
	<SubTexture name="Tulip_Idle0033" x="762" y="449" width="178" height="205"/>
	<SubTexture name="Tulip_Idle0034" x="762" y="449" width="178" height="205"/>
	<SubTexture name="Tulip_Idle0035" x="762" y="449" width="178" height="205"/>
	<SubTexture name="Tulip_Idle0036" x="762" y="449" width="178" height="205"/>
	<SubTexture name="Tulip_Idle0037" x="762" y="449" width="178" height="205"/>
	<SubTexture name="Tulip_Idle0038" x="762" y="449" width="178" height="205"/>
	<SubTexture name="Tulip_Idle0039" x="762" y="449" width="178" height="205"/>
	<SubTexture name="Tulip_Idle0040" x="762" y="449" width="178" height="205"/>
	<SubTexture name="Tulip_Idle0041" x="762" y="449" width="178" height="205"/>
	<SubTexture name="Tulip_Idle0042" x="762" y="449" width="178" height="205"/>
	<SubTexture name="Tulip_Idle0043" x="762" y="449" width="178" height="205"/>
	<SubTexture name="Tulip_Idle0044" x="762" y="449" width="178" height="205"/>
	<SubTexture name="Tulip_Idle0045" x="762" y="449" width="178" height="205"/>
	<SubTexture name="Tulip_Idle0046" x="762" y="449" width="178" height="205"/>
	<SubTexture name="Tulip_Idle0047" x="762" y="449" width="178" height="205"/>
	<SubTexture name="Tulip_Idle0048" x="762" y="449" width="178" height="205"/>
	<SubTexture name="Tulip_Idle0049" x="762" y="449" width="178" height="205"/>
	<SubTexture name="Tulip_Idle0050" x="762" y="449" width="178" height="205"/>
	<SubTexture name="Tulip_Idle0051" x="762" y="449" width="178" height="205"/>
	<SubTexture name="Tulip_Idle0052" x="762" y="449" width="178" height="205"/>
	<SubTexture name="Tulip_Idle0053" x="762" y="449" width="178" height="205"/>
	<SubTexture name="Tulip_Idle0054" x="762" y="449" width="178" height="205"/>
	<SubTexture name="Tulip_Idle0055" x="762" y="449" width="178" height="205"/>
	<SubTexture name="Tulip_Idle0056" x="762" y="449" width="178" height="205"/>
	<SubTexture name="Tulip_Idle0057" x="762" y="449" width="178" height="205"/>
	<SubTexture name="Tulip_Idle0058" x="762" y="449" width="178" height="205"/>
	<SubTexture name="Tulip_Idle0059" x="762" y="449" width="178" height="205"/>
	<SubTexture name="Tulip_Idle0060" x="762" y="449" width="178" height="205"/>
	<SubTexture name="Tulip_Idle0061" x="762" y="449" width="178" height="205"/>
	<SubTexture name="Tulip_Idle0062" x="762" y="449" width="178" height="205"/>
	<SubTexture name="Tulip_Idle0063" x="762" y="449" width="178" height="205"/>
	<SubTexture name="Tulip_Idle0064" x="762" y="449" width="178" height="205"/>
	<SubTexture name="Tulip_Idle0065" x="762" y="449" width="178" height="205"/>
	<SubTexture name="Tulip_Idle0066" x="762" y="449" width="178" height="205"/>
	<SubTexture name="Tulip_Idle0067" x="762" y="449" width="178" height="205"/>
	<SubTexture name="Tulip_Idle0068" x="762" y="449" width="178" height="205"/>
	<SubTexture name="Tulip_Idle0069" x="762" y="449" width="178" height="205"/>
	<SubTexture name="Tulip_Idle0070" x="762" y="449" width="178" height="205"/>
	<SubTexture name="Tulip_Idle0071" x="762" y="449" width="178" height="205"/>
	<SubTexture name="Tulip_Idle0072" x="762" y="449" width="178" height="205"/>
	<SubTexture name="Tulip_Idle0073" x="762" y="449" width="178" height="205"/>
	<SubTexture name="Tulip_Idle0074" x="762" y="449" width="178" height="205"/>
	<SubTexture name="Tulip_Idle0075" x="762" y="449" width="178" height="205"/>
	<SubTexture name="Tulip_Idle0076" x="762" y="449" width="178" height="205"/>
	<SubTexture name="Tulip_Idle0077" x="762" y="449" width="178" height="205"/>
	<SubTexture name="Tulip_Idle0078" x="762" y="449" width="178" height="205"/>
	<SubTexture name="Tulip_Idle0079" x="762" y="449" width="178" height="205"/>
	<SubTexture name="Tulip_Idle0080" x="762" y="449" width="178" height="205"/>
	<SubTexture name="Tulip_Idle0081" x="762" y="449" width="178" height="205"/>
	<SubTexture name="Tulip_Idle0082" x="762" y="449" width="178" height="205"/>
	<SubTexture name="Tulip_Idle0083" x="762" y="449" width="178" height="205"/>
	<SubTexture name="Tulip_Idle0084" x="762" y="449" width="178" height="205"/>
	<SubTexture name="Tulip_Idle0085" x="762" y="449" width="178" height="205"/>
	<SubTexture name="Tulip_Idle0086" x="762" y="449" width="178" height="205"/>
	<SubTexture name="Tulip_Idle0087" x="762" y="449" width="178" height="205"/>
	<SubTexture name="Tulip_Idle0088" x="762" y="449" width="178" height="205"/>
	<SubTexture name="Tulip_Idle0089" x="762" y="449" width="178" height="205"/>
	<SubTexture name="Tulip_LookAtDaisy0000" x="950" y="449" width="184" height="203"/>
	<SubTexture name="Tulip_LookAtDaisy0001" x="950" y="449" width="184" height="203"/>
	<SubTexture name="Tulip_LookAtDaisy0002" x="1144" y="449" width="184" height="203"/>
	<SubTexture name="Tulip_LookAtDaisy0003" x="1144" y="449" width="184" height="203"/>
	<SubTexture name="Tulip_LookAtDaisy0004" x="1338" y="449" width="184" height="203"/>
	<SubTexture name="Tulip_LookAtDaisy0005" x="1338" y="449" width="184" height="203"/>
	<SubTexture name="Tulip_LookAtDaisy0006" x="1338" y="449" width="184" height="203"/>
	<SubTexture name="Tulip_LookAtDaisy0007" x="1338" y="449" width="184" height="203"/>
	<SubTexture name="Tulip_LookAtDaisy0008" x="1338" y="449" width="184" height="203"/>
	<SubTexture name="Tulip_LookAtDaisy0009" x="1338" y="449" width="184" height="203"/>
	<SubTexture name="Tulip_LookAtDaisy0010" x="1338" y="449" width="184" height="203"/>
	<SubTexture name="Tulip_LookAtDaisy0011" x="1338" y="449" width="184" height="203"/>
	<SubTexture name="Tulip_LookAtDaisy0012" x="1338" y="449" width="184" height="203"/>
	<SubTexture name="Tulip_LookAtDaisy0013" x="1338" y="449" width="184" height="203"/>
	<SubTexture name="Tulip_LookAtDaisy0014" x="1338" y="449" width="184" height="203"/>
	<SubTexture name="Tulip_LookAtDaisy0015" x="1338" y="449" width="184" height="203"/>
	<SubTexture name="Tulip_LookAtDaisy0016" x="1338" y="449" width="184" height="203"/>
	<SubTexture name="Tulip_LookAtDaisy0017" x="1338" y="449" width="184" height="203"/>
	<SubTexture name="Tulip_LookAtDaisy0018" x="1338" y="449" width="184" height="203"/>
	<SubTexture name="Tulip_LookAtDaisy0019" x="1338" y="449" width="184" height="203"/>
	<SubTexture name="Tulip_LookAtDaisy0020" x="1338" y="449" width="184" height="203"/>
	<SubTexture name="Tulip_LookAtDaisy0021" x="1338" y="449" width="184" height="203"/>
	<SubTexture name="Tulip_LookAtDaisy0022" x="1338" y="449" width="184" height="203"/>
	<SubTexture name="Tulip_LookAtDaisy0023" x="1338" y="449" width="184" height="203"/>
	<SubTexture name="Tulip_LookAtDaisy0024" x="1338" y="449" width="184" height="203"/>
	<SubTexture name="Tulip_LookAtDaisy0025" x="1338" y="449" width="184" height="203"/>
	<SubTexture name="Tulip_LookAtDaisy0026" x="1338" y="449" width="184" height="203"/>
	<SubTexture name="Tulip_LookAtDaisy0027" x="1338" y="449" width="184" height="203"/>
	<SubTexture name="Tulip_LookAtDaisy0028" x="1338" y="449" width="184" height="203"/>
	<SubTexture name="Tulip_LookAtDaisy0029" x="1338" y="449" width="184" height="203"/>
	<SubTexture name="Tulip_LookAtDaisy0030" x="1338" y="449" width="184" height="203"/>
	<SubTexture name="Tulip_LookAtDaisy0031" x="1338" y="449" width="184" height="203"/>
	<SubTexture name="Tulip_LookAtDaisy0032" x="1338" y="449" width="184" height="203"/>
	<SubTexture name="Tulip_LookAtDaisy0033" x="1338" y="449" width="184" height="203"/>
	<SubTexture name="Tulip_LookAtDaisy0034" x="1338" y="449" width="184" height="203"/>
	<SubTexture name="Tulip_LookAtDaisy0035" x="1338" y="449" width="184" height="203"/>
	<SubTexture name="Tulip_LookAtDaisy0036" x="1338" y="449" width="184" height="203"/>
	<SubTexture name="Tulip_LookAtDaisy0037" x="1338" y="449" width="184" height="203"/>
	<SubTexture name="Tulip_LookAtDaisy0038" x="1338" y="449" width="184" height="203"/>
	<SubTexture name="Tulip_LookAtDaisy0039" x="1338" y="449" width="184" height="203"/>
	<SubTexture name="Tulip_LookAtDaisy0040" x="1338" y="449" width="184" height="203"/>
	<SubTexture name="Tulip_LookAtDaisy0041" x="1338" y="449" width="184" height="203"/>
	<SubTexture name="Tulip_LookAtDaisy0042" x="1338" y="449" width="184" height="203"/>
	<SubTexture name="Tulip_LookAtDaisy0043" x="1338" y="449" width="184" height="203"/>
	<SubTexture name="Tulip_LookAtDaisy0044" x="1338" y="449" width="184" height="203"/>
	<SubTexture name="Tulip_LookAtDaisy0045" x="1338" y="449" width="184" height="203"/>
	<SubTexture name="Tulip_LookAtDaisy0046" x="1338" y="449" width="184" height="203"/>
	<SubTexture name="Tulip_LookAtDaisy0047" x="1338" y="449" width="184" height="203"/>
	<SubTexture name="Tulip_LookAtDaisy0048" x="1338" y="449" width="184" height="203"/>
	<SubTexture name="Tulip_LookAtDaisy0049" x="1338" y="449" width="184" height="203"/>
	<SubTexture name="Tulip_LookAtDaisyStill0000" x="1144" y="449" width="184" height="203"/>
	<SubTexture name="Tulip_LookUp0000" x="1532" y="449" width="187" height="203"/>
	<SubTexture name="Tulip_LookUp0001" x="1532" y="449" width="187" height="203"/>
	<SubTexture name="Tulip_LookUp0002" x="1729" y="449" width="187" height="203"/>
	<SubTexture name="Tulip_LookUp0003" x="10" y="664" width="187" height="203"/>
	<SubTexture name="Tulip_LookUp0004" x="10" y="664" width="187" height="203"/>
	<SubTexture name="Tulip_LookUp0005" x="207" y="664" width="187" height="203"/>
	<SubTexture name="Tulip_LookUp0006" x="207" y="664" width="187" height="203"/>
	<SubTexture name="Tulip_LookUp0007" x="404" y="664" width="187" height="203"/>
	<SubTexture name="Tulip_LookUp0008" x="404" y="664" width="187" height="203"/>
	<SubTexture name="Tulip_LookUp0009" x="601" y="664" width="187" height="203"/>
	<SubTexture name="Tulip_LookUp0010" x="601" y="664" width="187" height="203"/>
	<SubTexture name="Tulip_LookUp0011" x="601" y="664" width="187" height="203"/>
	<SubTexture name="Tulip_LookUp0012" x="601" y="664" width="187" height="203"/>
	<SubTexture name="Tulip_LookUp0013" x="601" y="664" width="187" height="203"/>
	<SubTexture name="Tulip_LookUp0014" x="601" y="664" width="187" height="203"/>
	<SubTexture name="Tulip_LookUp0015" x="601" y="664" width="187" height="203"/>
	<SubTexture name="Tulip_LookUp0016" x="601" y="664" width="187" height="203"/>
	<SubTexture name="Tulip_LookUp0017" x="601" y="664" width="187" height="203"/>
	<SubTexture name="Tulip_LookUp0018" x="601" y="664" width="187" height="203"/>
	<SubTexture name="Tulip_LookUp0019" x="601" y="664" width="187" height="203"/>
	<SubTexture name="Tulip_LookUp0020" x="601" y="664" width="187" height="203"/>
	<SubTexture name="Tulip_LookUp0021" x="601" y="664" width="187" height="203"/>
	<SubTexture name="Tulip_LookUp0022" x="601" y="664" width="187" height="203"/>
	<SubTexture name="Tulip_LookUp0023" x="601" y="664" width="187" height="203"/>
	<SubTexture name="Tulip_LookUpStill0000" x="798" y="664" width="187" height="203"/>
	<SubTexture name="Tulip_LookUpStill0001" x="798" y="664" width="187" height="203"/>
	<SubTexture name="Tulip_LookUpStill0002" x="798" y="664" width="187" height="203"/>
	<SubTexture name="Tulip_LookUpStill0003" x="798" y="664" width="187" height="203"/>
	<SubTexture name="Tulip_LookUpStill0004" x="798" y="664" width="187" height="203"/>
	<SubTexture name="Tulip_LookUpStill0005" x="798" y="664" width="187" height="203"/>
	<SubTexture name="Tulip_LookUpStill0006" x="798" y="664" width="187" height="203"/>
	<SubTexture name="Tulip_LookUpStill0007" x="798" y="664" width="187" height="203"/>
	<SubTexture name="Tulip_LookUpStill0008" x="995" y="664" width="187" height="203"/>
	<SubTexture name="Tulip_LookUpStill0009" x="995" y="664" width="187" height="203"/>
	<SubTexture name="Tulip_LookUpStill0010" x="1192" y="664" width="187" height="203"/>
	<SubTexture name="Tulip_LookUpStill0011" x="1192" y="664" width="187" height="203"/>
	<SubTexture name="Tulip_LookUpStill0012" x="1389" y="664" width="187" height="203"/>
	<SubTexture name="Tulip_LookUpStill0013" x="1389" y="664" width="187" height="203"/>
	<SubTexture name="Tulip_LookUpStill0014" x="798" y="664" width="187" height="203"/>
	<SubTexture name="Tulip_LookUpStill0015" x="798" y="664" width="187" height="203"/>
	<SubTexture name="Tulip_LookUpStill0016" x="798" y="664" width="187" height="203"/>
	<SubTexture name="Tulip_LookUpStill0017" x="798" y="664" width="187" height="203"/>
	<SubTexture name="Tulip_LookUpStill0018" x="798" y="664" width="187" height="203"/>
	<SubTexture name="Tulip_LookUpStill0019" x="798" y="664" width="187" height="203"/>
	<SubTexture name="Tulip_LookUpStill0020" x="798" y="664" width="187" height="203"/>
	<SubTexture name="Tulip_LookUpStill0021" x="798" y="664" width="187" height="203"/>
	<SubTexture name="Tulip_LookUpStill0022" x="798" y="664" width="187" height="203"/>
	<SubTexture name="Tulip_LookUpStill0023" x="798" y="664" width="187" height="203"/>
	<SubTexture name="Tulip_LookUpStill0024" x="798" y="664" width="187" height="203"/>
	<SubTexture name="Tulip_LookUpStill0025" x="798" y="664" width="187" height="203"/>
	<SubTexture name="Tulip_LookUpStill0026" x="798" y="664" width="187" height="203"/>
	<SubTexture name="Tulip_LookUpStill0027" x="798" y="664" width="187" height="203"/>
	<SubTexture name="Tulip_LookUpStill0028" x="798" y="664" width="187" height="203"/>
	<SubTexture name="Tulip_LookUpStill0029" x="798" y="664" width="187" height="203"/>
	<SubTexture name="Tulip_LookUpStill0030" x="798" y="664" width="187" height="203"/>
	<SubTexture name="Tulip_LookUpStill0031" x="798" y="664" width="187" height="203"/>
	<SubTexture name="Tulip_LookUpStill0032" x="798" y="664" width="187" height="203"/>
	<SubTexture name="Tulip_LookUpStill0033" x="798" y="664" width="187" height="203"/>
	<SubTexture name="Tulip_LookUpStill0034" x="798" y="664" width="187" height="203"/>
	<SubTexture name="Tulip_LookUpStill0035" x="798" y="664" width="187" height="203"/>
	<SubTexture name="Tulip_LookUpStill0036" x="798" y="664" width="187" height="203"/>
	<SubTexture name="Tulip_LookUpStill0037" x="798" y="664" width="187" height="203"/>
	<SubTexture name="Tulip_LookUpStill0038" x="798" y="664" width="187" height="203"/>
	<SubTexture name="Tulip_LookUpStill0039" x="798" y="664" width="187" height="203"/>
	<SubTexture name="Tulip_LookUpStill0040" x="798" y="664" width="187" height="203"/>
	<SubTexture name="Tulip_LookUpStill0041" x="798" y="664" width="187" height="203"/>
	<SubTexture name="Tulip_LookUpStill0042" x="798" y="664" width="187" height="203"/>
	<SubTexture name="Tulip_LookUpStill0043" x="798" y="664" width="187" height="203"/>
	<SubTexture name="Tulip_LookUpStill0044" x="798" y="664" width="187" height="203"/>
	<SubTexture name="Tulip_LookUpStill0045" x="798" y="664" width="187" height="203"/>
	<SubTexture name="Tulip_LookUpStill0046" x="798" y="664" width="187" height="203"/>
	<SubTexture name="Tulip_LookUpStill0047" x="798" y="664" width="187" height="203"/>
	<SubTexture name="Tulip_LookUpStill0048" x="798" y="664" width="187" height="203"/>
	<SubTexture name="Tulip_LookUpStill0049" x="798" y="664" width="187" height="203"/>
</TextureAtlas>
